{"npcData":{"npcClassId":1078,"level":70,"npcType":1,"acquireExpRate":16962.5701,"acquireSp":1682,"skillList":[{"skillId":4298,"skillLevel":1},{"skillId":4303,"skillLevel":1},{"skillId":4278,"skillLevel":1},{"skillId":4333,"skillLevel":3},{"skillId":4084,"skillLevel":1},{"skillId":4281,"skillLevel":2},{"skillId":4276,"skillLevel":1}],"corpseMakeList":[{"itemClassId":4040,"min":1,"max":1,"chance":11.0398},{"itemClassId":4085,"min":1,"max":1,"chance":19.8266},{"itemClassId":3956,"min":1,"max":1,"chance":0.736}],"additionalMakeList":[],"additionalMakeMultiList":[{"itemClassId":57,"min":2226,"max":4530,"chance":70},{"itemClassId":110,"min":1,"max":1,"chance":0.006431981799999999},{"itemClassId":4077,"min":1,"max":1,"chance":1.2223695033000002},{"itemClassId":2416,"min":1,"max":1,"chance":0.0044898788},{"itemClassId":4088,"min":1,"max":1,"chance":1.0269577328},{"itemClassId":2417,"min":1,"max":1,"chance":0.0044898788},{"itemClassId":4089,"min":1,"max":1,"chance":1.0269610245},{"itemClassId":1873,"min":1,"max":1,"chance":10.869904174},{"itemClassId":1868,"min":3,"max":9,"chance":9.0582421104},{"itemClassId":1876,"min":1,"max":1,"chance":5.434952087},{"itemClassId":1895,"min":1,"max":1,"chance":7.7642075232000005},{"itemClassId":4042,"min":1,"max":1,"chance":0.452898464},{"itemClassId":4175,"min":1,"max":1,"chance":0.5235956414}],"orgHp":7724,"orgMp":1493,"baseDefend":513,"baseMagicAttack":779,"baseMagicDefend":381,"basePhysicalAttack":1444,"physicalHitModify":0,"physicalAvoidModify":0,"baseAttackSpeed":253,"baseCritical":11,"social":true},"drop":[{"npcId":1078,"min":2226,"max":4530,"chance":70,"crystal":{"itemClassId":57,"crystalType":"NoGrade"},"npcType":1},{"npcId":1078,"min":1,"max":1,"chance":10.8699,"crystal":{"itemClassId":1873,"crystalType":"NoGrade"},"npcType":1},{"npcId":1078,"min":3,"max":9,"chance":9.05824,"crystal":{"itemClassId":1868,"crystalType":"NoGrade"},"npcType":1},{"npcId":1078,"min":1,"max":1,"chance":7.76421,"crystal":{"itemClassId":1895,"crystalType":"NoGrade"},"npcType":1},{"npcId":1078,"min":1,"max":1,"chance":5.43495,"crystal":{"itemClassId":1876,"crystalType":"NoGrade"},"npcType":1},{"npcId":1078,"min":1,"max":1,"chance":1.22237,"crystal":{"itemClassId":4077,"crystalType":"NoGrade"},"npcType":1},{"npcId":1078,"min":1,"max":1,"chance":1.02696,"crystal":{"itemClassId":4088,"crystalType":"NoGrade"},"npcType":1},{"npcId":1078,"min":1,"max":1,"chance":1.02696,"crystal":{"itemClassId":4089,"crystalType":"NoGrade"},"npcType":1},{"npcId":1078,"min":1,"max":1,"chance":0.5236,"crystal":{"itemClassId":4175,"crystalType":"NoGrade"},"npcType":1},{"npcId":1078,"min":1,"max":1,"chance":0.4529,"crystal":{"itemClassId":4042,"crystalType":"NoGrade"},"npcType":1},{"npcId":1078,"min":1,"max":1,"chance":0.00643,"crystal":{"itemClassId":110,"crystalType":"B"},"npcType":1},{"npcId":1078,"min":1,"max":1,"chance":0.00449,"crystal":{"itemClassId":2416,"crystalType":"B"},"npcType":1},{"npcId":1078,"min":1,"max":1,"chance":0.00449,"crystal":{"itemClassId":2417,"crystalType":"B"},"npcType":1}],"spoil":[{"npcId":1078,"min":1,"max":1,"chance":19.8266,"crystal":{"itemClassId":4085,"crystalType":"NoGrade"},"npcType":1},{"npcId":1078,"min":1,"max":1,"chance":11.0398,"crystal":{"itemClassId":4040,"crystalType":"NoGrade"},"npcType":1},{"npcId":1078,"min":1,"max":1,"chance":0.736,"crystal":{"itemClassId":3956,"crystalType":"NoGrade"},"npcType":1}]}