{"npcData":{"npcClassId":213,"level":40,"npcType":1,"acquireExpRate":4728.6752,"acquireSp":305,"skillList":[{"skillId":4274,"skillLevel":1},{"skillId":4303,"skillLevel":1},{"skillId":4084,"skillLevel":1},{"skillId":4291,"skillLevel":1}],"corpseMakeList":[{"itemClassId":2292,"min":1,"max":1,"chance":0.7934},{"itemClassId":1894,"min":1,"max":1,"chance":5.0112},{"itemClassId":1884,"min":1,"max":1,"chance":87.8893}],"additionalMakeList":[],"additionalMakeMultiList":[{"itemClassId":57,"min":599,"max":1195,"chance":70},{"itemClassId":352,"min":1,"max":1,"chance":0.0082303713},{"itemClassId":1941,"min":1,"max":1,"chance":0.4892835724},{"itemClassId":2377,"min":1,"max":1,"chance":0.0131578821},{"itemClassId":2918,"min":1,"max":1,"chance":0.7299341542},{"itemClassId":2378,"min":1,"max":1,"chance":0.0131578821},{"itemClassId":2919,"min":1,"max":1,"chance":0.7299361379},{"itemClassId":1864,"min":1,"max":3,"chance":6.1522493878},{"itemClassId":1869,"min":1,"max":1,"chance":9.228374081699998},{"itemClassId":1878,"min":1,"max":1,"chance":3.6913414602999994},{"itemClassId":1884,"min":1,"max":1,"chance":5.6789868619999995},{"itemClassId":2983,"min":1,"max":1,"chance":0.6277613697},{"itemClassId":2286,"min":1,"max":1,"chance":0.051281684499999994},{"itemClassId":2290,"min":1,"max":1,"chance":0.051281684499999994},{"itemClassId":1341,"min":20,"max":60,"chance":15.380623469500001}],"orgHp":3054,"orgMp":531,"baseDefend":266,"baseMagicAttack":131,"baseMagicDefend":163,"basePhysicalAttack":247,"physicalHitModify":0,"physicalAvoidModify":0,"baseAttackSpeed":253,"baseCritical":11,"social":true},"drop":[{"npcId":213,"min":599,"max":1195,"chance":70,"crystal":{"itemClassId":57,"crystalType":"NoGrade"},"npcType":1},{"npcId":213,"min":20,"max":60,"chance":15.38062,"crystal":{"itemClassId":1341,"crystalType":"D"},"npcType":1},{"npcId":213,"min":1,"max":1,"chance":9.22837,"crystal":{"itemClassId":1869,"crystalType":"NoGrade"},"npcType":1},{"npcId":213,"min":1,"max":3,"chance":6.15225,"crystal":{"itemClassId":1864,"crystalType":"NoGrade"},"npcType":1},{"npcId":213,"min":1,"max":1,"chance":5.67899,"crystal":{"itemClassId":1884,"crystalType":"NoGrade"},"npcType":1},{"npcId":213,"min":1,"max":1,"chance":3.69134,"crystal":{"itemClassId":1878,"crystalType":"NoGrade"},"npcType":1},{"npcId":213,"min":1,"max":1,"chance":0.72994,"crystal":{"itemClassId":2919,"crystalType":"NoGrade"},"npcType":1},{"npcId":213,"min":1,"max":1,"chance":0.72993,"crystal":{"itemClassId":2918,"crystalType":"NoGrade"},"npcType":1},{"npcId":213,"min":1,"max":1,"chance":0.62776,"crystal":{"itemClassId":2983,"crystalType":"NoGrade"},"npcType":1},{"npcId":213,"min":1,"max":1,"chance":0.48928,"crystal":{"itemClassId":1941,"crystalType":"NoGrade"},"npcType":1},{"npcId":213,"min":1,"max":1,"chance":0.05128,"crystal":{"itemClassId":2286,"crystalType":"NoGrade"},"npcType":1},{"npcId":213,"min":1,"max":1,"chance":0.05128,"crystal":{"itemClassId":2290,"crystalType":"NoGrade"},"npcType":1},{"npcId":213,"min":1,"max":1,"chance":0.01316,"crystal":{"itemClassId":2377,"crystalType":"D"},"npcType":1},{"npcId":213,"min":1,"max":1,"chance":0.01316,"crystal":{"itemClassId":2378,"crystalType":"D"},"npcType":1},{"npcId":213,"min":1,"max":1,"chance":0.00823,"crystal":{"itemClassId":352,"crystalType":"D"},"npcType":1}],"spoil":[{"npcId":213,"min":1,"max":1,"chance":87.8893,"crystal":{"itemClassId":1884,"crystalType":"NoGrade"},"npcType":1},{"npcId":213,"min":1,"max":1,"chance":5.0112,"crystal":{"itemClassId":1894,"crystalType":"NoGrade"},"npcType":1},{"npcId":213,"min":1,"max":1,"chance":0.7934,"crystal":{"itemClassId":2292,"crystalType":"NoGrade"},"npcType":1}]}