{"npcData":{"npcClassId":946,"level":52,"npcType":1,"acquireExpRate":3448.189472,"acquireSp":267,"skillList":[{"skillId":4292,"skillLevel":1},{"skillId":4311,"skillLevel":1}],"corpseMakeList":[{"itemClassId":1539,"min":1,"max":1,"chance":25.1226},{"itemClassId":1914,"min":1,"max":1,"chance":6.3512},{"itemClassId":2169,"min":1,"max":1,"chance":2.0009}],"additionalMakeList":[],"additionalMakeMultiList":[{"itemClassId":57,"min":458,"max":926,"chance":70},{"itemClassId":103,"min":1,"max":1,"chance":0.0045302284},{"itemClassId":1978,"min":1,"max":1,"chance":0.37459381959999993},{"itemClassId":107,"min":1,"max":1,"chance":0.0045302284},{"itemClassId":4055,"min":1,"max":1,"chance":0.37459381959999993},{"itemClassId":517,"min":1,"max":1,"chance":0.0031763964},{"itemClassId":2957,"min":1,"max":1,"chance":0.2563008328},{"itemClassId":1149,"min":1,"max":1,"chance":0.0031763964},{"itemClassId":1983,"min":1,"max":1,"chance":0.25629827839999997},{"itemClassId":1864,"min":1,"max":1,"chance":13.3575048239},{"itemClassId":1869,"min":1,"max":1,"chance":6.6787663344},{"itemClassId":1878,"min":1,"max":1,"chance":2.6714953958},{"itemClassId":1884,"min":1,"max":1,"chance":4.1099907747},{"itemClassId":4039,"min":1,"max":1,"chance":0.2226199755},{"itemClassId":2233,"min":1,"max":1,"chance":0.0624282658},{"itemClassId":4180,"min":1,"max":1,"chance":0.7420944298999999}],"orgHp":1201,"orgMp":892,"baseDefend":294,"baseMagicAttack":300,"baseMagicDefend":239,"basePhysicalAttack":570,"physicalHitModify":0,"physicalAvoidModify":0,"baseAttackSpeed":253,"baseCritical":11,"social":true},"drop":[{"npcId":946,"min":458,"max":926,"chance":70,"crystal":{"itemClassId":57,"crystalType":"NoGrade"},"npcType":1},{"npcId":946,"min":1,"max":1,"chance":13.3575,"crystal":{"itemClassId":1864,"crystalType":"NoGrade"},"npcType":1},{"npcId":946,"min":1,"max":1,"chance":6.67877,"crystal":{"itemClassId":1869,"crystalType":"NoGrade"},"npcType":1},{"npcId":946,"min":1,"max":1,"chance":4.10999,"crystal":{"itemClassId":1884,"crystalType":"NoGrade"},"npcType":1},{"npcId":946,"min":1,"max":1,"chance":2.6715,"crystal":{"itemClassId":1878,"crystalType":"NoGrade"},"npcType":1},{"npcId":946,"min":1,"max":1,"chance":0.74209,"crystal":{"itemClassId":4180,"crystalType":"NoGrade"},"npcType":1},{"npcId":946,"min":1,"max":1,"chance":0.37459,"crystal":{"itemClassId":1978,"crystalType":"NoGrade"},"npcType":1},{"npcId":946,"min":1,"max":1,"chance":0.37459,"crystal":{"itemClassId":4055,"crystalType":"NoGrade"},"npcType":1},{"npcId":946,"min":1,"max":1,"chance":0.2563,"crystal":{"itemClassId":2957,"crystalType":"NoGrade"},"npcType":1},{"npcId":946,"min":1,"max":1,"chance":0.2563,"crystal":{"itemClassId":1983,"crystalType":"NoGrade"},"npcType":1},{"npcId":946,"min":1,"max":1,"chance":0.22262,"crystal":{"itemClassId":4039,"crystalType":"NoGrade"},"npcType":1},{"npcId":946,"min":1,"max":1,"chance":0.06243,"crystal":{"itemClassId":2233,"crystalType":"NoGrade"},"npcType":1},{"npcId":946,"min":1,"max":1,"chance":0.00453,"crystal":{"itemClassId":103,"crystalType":"C"},"npcType":1},{"npcId":946,"min":1,"max":1,"chance":0.00453,"crystal":{"itemClassId":107,"crystalType":"C"},"npcType":1},{"npcId":946,"min":1,"max":1,"chance":0.00318,"crystal":{"itemClassId":517,"crystalType":"C"},"npcType":1},{"npcId":946,"min":1,"max":1,"chance":0.00318,"crystal":{"itemClassId":1149,"crystalType":"C"},"npcType":1}],"spoil":[{"npcId":946,"min":1,"max":1,"chance":25.1226,"crystal":{"itemClassId":1539,"crystalType":"NoGrade"},"npcType":1},{"npcId":946,"min":1,"max":1,"chance":6.3512,"crystal":{"itemClassId":1914,"crystalType":"NoGrade"},"npcType":1},{"npcId":946,"min":1,"max":1,"chance":2.0009,"crystal":{"itemClassId":2169,"crystalType":"NoGrade"},"npcType":1}]}