{"npcData":{"npcClassId":1017,"level":55,"npcType":1,"acquireExpRate":4399.5599999999995,"acquireSp":355,"skillList":[],"corpseMakeList":[{"itemClassId":1989,"min":1,"max":1,"chance":4.3688},{"itemClassId":1880,"min":1,"max":1,"chance":14.4955},{"itemClassId":1806,"min":1,"max":1,"chance":0.2899}],"additionalMakeList":[],"additionalMakeMultiList":[{"itemClassId":57,"min":584,"max":1190,"chance":70},{"itemClassId":400,"min":1,"max":1,"chance":0.0021625290000000003},{"itemClassId":1984,"min":1,"max":1,"chance":0.19122788340000002},{"itemClassId":401,"min":1,"max":1,"chance":0.0011364507000000002},{"itemClassId":1987,"min":1,"max":1,"chance":0.13610200320000002},{"itemClassId":420,"min":1,"max":1,"chance":0.0034574795999999996},{"itemClassId":1985,"min":1,"max":1,"chance":0.3076136541},{"itemClassId":1866,"min":1,"max":1,"chance":4.460175521999999},{"itemClassId":1871,"min":1,"max":1,"chance":6.690263283},{"itemClassId":5220,"min":1,"max":1,"chance":0.26760617999999997},{"itemClassId":1885,"min":1,"max":1,"chance":0.557524962},{"itemClassId":4041,"min":1,"max":1,"chance":0.058174731},{"itemClassId":4940,"min":1,"max":1,"chance":0.032163507},{"itemClassId":5280,"min":1,"max":1,"chance":0.013380309000000002},{"itemClassId":4189,"min":1,"max":1,"chance":0.007711505999999999}],"orgHp":2643,"orgMp":987,"baseDefend":292,"baseMagicAttack":360,"baseMagicDefend":260,"basePhysicalAttack":736,"physicalHitModify":0,"physicalAvoidModify":0,"baseAttackSpeed":253,"baseCritical":44,"social":true},"drop":[{"npcId":1017,"min":584,"max":1190,"chance":70,"crystal":{"itemClassId":57,"crystalType":"NoGrade"},"npcType":1},{"npcId":1017,"min":1,"max":1,"chance":6.69026,"crystal":{"itemClassId":1871,"crystalType":"NoGrade"},"npcType":1},{"npcId":1017,"min":1,"max":1,"chance":4.46018,"crystal":{"itemClassId":1866,"crystalType":"NoGrade"},"npcType":1},{"npcId":1017,"min":1,"max":1,"chance":0.55752,"crystal":{"itemClassId":1885,"crystalType":"NoGrade"},"npcType":1},{"npcId":1017,"min":1,"max":1,"chance":0.30761,"crystal":{"itemClassId":1985,"crystalType":"NoGrade"},"npcType":1},{"npcId":1017,"min":1,"max":1,"chance":0.26761,"crystal":{"itemClassId":5220,"crystalType":"NoGrade"},"npcType":1},{"npcId":1017,"min":1,"max":1,"chance":0.19123,"crystal":{"itemClassId":1984,"crystalType":"NoGrade"},"npcType":1},{"npcId":1017,"min":1,"max":1,"chance":0.1361,"crystal":{"itemClassId":1987,"crystalType":"NoGrade"},"npcType":1},{"npcId":1017,"min":1,"max":1,"chance":0.05817,"crystal":{"itemClassId":4041,"crystalType":"NoGrade"},"npcType":1},{"npcId":1017,"min":1,"max":1,"chance":0.03216,"crystal":{"itemClassId":4940,"crystalType":"NoGrade"},"npcType":1},{"npcId":1017,"min":1,"max":1,"chance":0.01338,"crystal":{"itemClassId":5280,"crystalType":"NoGrade"},"npcType":1},{"npcId":1017,"min":1,"max":1,"chance":0.00771,"crystal":{"itemClassId":4189,"crystalType":"NoGrade"},"npcType":1},{"npcId":1017,"min":1,"max":1,"chance":0.00346,"crystal":{"itemClassId":420,"crystalType":"C"},"npcType":1},{"npcId":1017,"min":1,"max":1,"chance":0.00216,"crystal":{"itemClassId":400,"crystalType":"C"},"npcType":1},{"npcId":1017,"min":1,"max":1,"chance":0.00114,"crystal":{"itemClassId":401,"crystalType":"C"},"npcType":1}],"spoil":[{"npcId":1017,"min":1,"max":1,"chance":14.4955,"crystal":{"itemClassId":1880,"crystalType":"NoGrade"},"npcType":1},{"npcId":1017,"min":1,"max":1,"chance":4.3688,"crystal":{"itemClassId":1989,"crystalType":"NoGrade"},"npcType":1},{"npcId":1017,"min":1,"max":1,"chance":0.2899,"crystal":{"itemClassId":1806,"crystalType":"NoGrade"},"npcType":1}]}