{"npcData":{"npcClassId":238,"level":48,"npcType":1,"acquireExpRate":3064.32,"acquireSp":224,"skillList":[{"skillId":4004,"skillLevel":1},{"skillId":4007,"skillLevel":1}],"corpseMakeList":[{"itemClassId":2357,"min":1,"max":1,"chance":0.21230000000000002},{"itemClassId":1877,"min":1,"max":1,"chance":5.2062},{"itemClassId":4041,"min":1,"max":1,"chance":1.1318}],"additionalMakeList":[],"additionalMakeMultiList":[{"itemClassId":57,"min":525,"max":1067,"chance":70},{"itemClassId":355,"min":1,"max":1,"chance":0.0044772},{"itemClassId":1968,"min":1,"max":1,"chance":0.34738522000000005},{"itemClassId":382,"min":1,"max":1,"chance":0.00715442},{"itemClassId":1969,"min":1,"max":1,"chance":0.55098316},{"itemClassId":1869,"min":1,"max":3,"chance":5.6217311305},{"itemClassId":1877,"min":1,"max":3,"chance":0.2248736931},{"itemClassId":1880,"min":1,"max":3,"chance":0.5621786729},{"itemClassId":2345,"min":1,"max":1,"chance":0.0261424147},{"itemClassId":2508,"min":1,"max":3,"chance":4.6847740888}],"orgHp":2091,"orgMp":768,"baseDefend":261,"baseMagicAttack":231,"baseMagicDefend":211,"basePhysicalAttack":498,"physicalHitModify":-6,"physicalAvoidModify":0,"baseAttackSpeed":253,"baseCritical":44,"social":true},"drop":[{"npcId":238,"min":525,"max":1067,"chance":70,"crystal":{"itemClassId":57,"crystalType":"NoGrade"},"npcType":1},{"npcId":238,"min":1,"max":3,"chance":5.62173,"crystal":{"itemClassId":1869,"crystalType":"NoGrade"},"npcType":1},{"npcId":238,"min":1,"max":3,"chance":4.68477,"crystal":{"itemClassId":2508,"crystalType":"NoGrade"},"npcType":1},{"npcId":238,"min":1,"max":3,"chance":0.56218,"crystal":{"itemClassId":1880,"crystalType":"NoGrade"},"npcType":1},{"npcId":238,"min":1,"max":1,"chance":0.55098,"crystal":{"itemClassId":1969,"crystalType":"NoGrade"},"npcType":1},{"npcId":238,"min":1,"max":1,"chance":0.34739,"crystal":{"itemClassId":1968,"crystalType":"NoGrade"},"npcType":1},{"npcId":238,"min":1,"max":3,"chance":0.22487,"crystal":{"itemClassId":1877,"crystalType":"NoGrade"},"npcType":1},{"npcId":238,"min":1,"max":1,"chance":0.02614,"crystal":{"itemClassId":2345,"crystalType":"NoGrade"},"npcType":1},{"npcId":238,"min":1,"max":1,"chance":0.00715,"crystal":{"itemClassId":382,"crystalType":"C"},"npcType":1},{"npcId":238,"min":1,"max":1,"chance":0.00448,"crystal":{"itemClassId":355,"crystalType":"C"},"npcType":1}],"spoil":[{"npcId":238,"min":1,"max":1,"chance":5.2062,"crystal":{"itemClassId":1877,"crystalType":"NoGrade"},"npcType":1},{"npcId":238,"min":1,"max":1,"chance":1.1318,"crystal":{"itemClassId":4041,"crystalType":"NoGrade"},"npcType":1},{"npcId":238,"min":1,"max":1,"chance":0.2123,"crystal":{"itemClassId":2357,"crystalType":"NoGrade"},"npcType":1}]}