{"npcData":{"npcClassId":963,"level":68,"npcType":1,"acquireExpRate":4691.3809280000005,"acquireSp":453,"skillList":[{"skillId":4278,"skillLevel":1},{"skillId":4333,"skillLevel":3},{"skillId":4086,"skillLevel":1},{"skillId":4116,"skillLevel":1}],"corpseMakeList":[{"itemClassId":4116,"min":1,"max":1,"chance":0.7834},{"itemClassId":4083,"min":1,"max":1,"chance":3.8682999999999996},{"itemClassId":4084,"min":1,"max":1,"chance":6.4391}],"additionalMakeList":[],"additionalMakeMultiList":[{"itemClassId":57,"min":723,"max":1470,"chance":70},{"itemClassId":2439,"min":1,"max":1,"chance":0.0016468478},{"itemClassId":4090,"min":1,"max":1,"chance":0.29712815220000005},{"itemClassId":601,"min":1,"max":1,"chance":0.0016468478},{"itemClassId":4099,"min":1,"max":1,"chance":0.29712815220000005},{"itemClassId":2487,"min":1,"max":1,"chance":0.0016468478},{"itemClassId":4096,"min":1,"max":1,"chance":0.29712815220000005},{"itemClassId":2475,"min":1,"max":1,"chance":0.0016468478},{"itemClassId":4091,"min":1,"max":1,"chance":0.29712815220000005},{"itemClassId":1869,"min":1,"max":1,"chance":8.825567507099999},{"itemClassId":1864,"min":1,"max":1,"chance":17.651135014199998},{"itemClassId":1880,"min":1,"max":1,"chance":0.8825539711},{"itemClassId":4041,"min":1,"max":1,"chance":0.11766089129999999},{"itemClassId":4043,"min":1,"max":1,"chance":0.29419392240000003},{"itemClassId":4984,"min":1,"max":1,"chance":0.024988693899999997}],"orgHp":1853,"orgMp":1423,"baseDefend":381,"baseMagicAttack":713,"baseMagicDefend":437,"basePhysicalAttack":1217,"physicalHitModify":10,"physicalAvoidModify":0,"baseAttackSpeed":253,"baseCritical":16,"social":true},"drop":[{"npcId":963,"min":723,"max":1470,"chance":70,"crystal":{"itemClassId":57,"crystalType":"NoGrade"},"npcType":1},{"npcId":963,"min":1,"max":1,"chance":17.65114,"crystal":{"itemClassId":1864,"crystalType":"NoGrade"},"npcType":1},{"npcId":963,"min":1,"max":1,"chance":8.82557,"crystal":{"itemClassId":1869,"crystalType":"NoGrade"},"npcType":1},{"npcId":963,"min":1,"max":1,"chance":0.88255,"crystal":{"itemClassId":1880,"crystalType":"NoGrade"},"npcType":1},{"npcId":963,"min":1,"max":1,"chance":0.29713,"crystal":{"itemClassId":4090,"crystalType":"NoGrade"},"npcType":1},{"npcId":963,"min":1,"max":1,"chance":0.29713,"crystal":{"itemClassId":4099,"crystalType":"NoGrade"},"npcType":1},{"npcId":963,"min":1,"max":1,"chance":0.29713,"crystal":{"itemClassId":4096,"crystalType":"NoGrade"},"npcType":1},{"npcId":963,"min":1,"max":1,"chance":0.29713,"crystal":{"itemClassId":4091,"crystalType":"NoGrade"},"npcType":1},{"npcId":963,"min":1,"max":1,"chance":0.29419,"crystal":{"itemClassId":4043,"crystalType":"NoGrade"},"npcType":1},{"npcId":963,"min":1,"max":1,"chance":0.11766,"crystal":{"itemClassId":4041,"crystalType":"NoGrade"},"npcType":1},{"npcId":963,"min":1,"max":1,"chance":0.02499,"crystal":{"itemClassId":4984,"crystalType":"NoGrade"},"npcType":1},{"npcId":963,"min":1,"max":1,"chance":0.00165,"crystal":{"itemClassId":2439,"crystalType":"B"},"npcType":1},{"npcId":963,"min":1,"max":1,"chance":0.00165,"crystal":{"itemClassId":601,"crystalType":"B"},"npcType":1},{"npcId":963,"min":1,"max":1,"chance":0.00165,"crystal":{"itemClassId":2487,"crystalType":"B"},"npcType":1},{"npcId":963,"min":1,"max":1,"chance":0.00165,"crystal":{"itemClassId":2475,"crystalType":"B"},"npcType":1}],"spoil":[{"npcId":963,"min":1,"max":1,"chance":6.4391,"crystal":{"itemClassId":4084,"crystalType":"NoGrade"},"npcType":1},{"npcId":963,"min":1,"max":1,"chance":3.8683,"crystal":{"itemClassId":4083,"crystalType":"NoGrade"},"npcType":1},{"npcId":963,"min":1,"max":1,"chance":0.7834,"crystal":{"itemClassId":4116,"crystalType":"NoGrade"},"npcType":1}]}