{"npcData":{"npcClassId":20043,"level":19,"npcType":1,"acquireExpRate":2282.735487,"acquireSp":102,"skillList":[{"skillId":4416,"skillLevel":12},{"skillId":4408,"skillLevel":1},{"skillId":4409,"skillLevel":1},{"skillId":4410,"skillLevel":10},{"skillId":4411,"skillLevel":10},{"skillId":4412,"skillLevel":12},{"skillId":4413,"skillLevel":12},{"skillId":4414,"skillLevel":2},{"skillId":4415,"skillLevel":3},{"skillId":4279,"skillLevel":1}],"magicList":[],"corpseMakeList":[{"itemClassId":1817,"min":1,"max":1,"chance":17.5824},{"itemClassId":1924,"min":1,"max":1,"chance":28.3587},{"itemClassId":1864,"min":1,"max":2,"chance":100}],"additionalMakeList":[],"additionalMakeMultiList":[{"itemClassId":57,"min":360,"max":615,"chance":70},{"itemClassId":2,"min":1,"max":1,"chance":0.024731880300000002},{"itemClassId":120,"min":1,"max":1,"chance":0.024731880300000002},{"itemClassId":2012,"min":1,"max":1,"chance":0.27050435910000004},{"itemClassId":121,"min":1,"max":1,"chance":0.024731880300000002},{"itemClassId":1864,"min":1,"max":1,"chance":12.9839600118},{"itemClassId":1865,"min":1,"max":1,"chance":6.491950878600001},{"itemClassId":1866,"min":1,"max":1,"chance":4.327967252400001},{"itemClassId":1873,"min":1,"max":1,"chance":2.5968153042},{"itemClassId":1868,"min":1,"max":1,"chance":12.9839600118},{"itemClassId":2143,"min":1,"max":1,"chance":1.2983785248000002},{"itemClassId":5158,"min":1,"max":1,"chance":0.25969900679999997},{"itemClassId":1831,"min":1,"max":1,"chance":17.311869009600002}],"exItemDropList":[{"itemClassId":8600,"min":1,"max":1,"chance":23.1},{"itemClassId":8601,"min":1,"max":1,"chance":15.96},{"itemClassId":8611,"min":1,"max":1,"chance":10.34},{"itemClassId":8604,"min":1,"max":1,"chance":5.72},{"itemClassId":8606,"min":1,"max":1,"chance":5},{"itemClassId":8608,"min":1,"max":1,"chance":5},{"itemClassId":8610,"min":1,"max":1,"chance":5},{"itemClassId":8607,"min":1,"max":1,"chance":5},{"itemClassId":8609,"min":1,"max":1,"chance":5},{"itemClassId":8603,"min":1,"max":1,"chance":4.4},{"itemClassId":8602,"min":1,"max":1,"chance":2.94},{"itemClassId":8605,"min":1,"max":1,"chance":0.88},{"itemClassId":8614,"min":1,"max":1,"chance":0.34},{"itemClassId":8612,"min":1,"max":1,"chance":0.33},{"itemClassId":8613,"min":1,"max":1,"chance":0.33}],"orgHp":508,"orgMp":223,"baseDefend":99,"baseMagicAttack":17,"baseMagicDefend":79,"basePhysicalAttack":47,"physicalHitModify":0,"physicalAvoidModify":0,"baseAttackSpeed":253,"baseCritical":44,"social":true},"drop":[{"npcId":20043,"min":360,"max":615,"chance":70,"crystal":{"itemClassId":57,"crystalType":"NoGrade","count":0},"npcType":1},{"npcId":20043,"min":1,"max":1,"chance":17.31187,"crystal":{"itemClassId":1831,"crystalType":"NoGrade","count":0},"npcType":1},{"npcId":20043,"min":1,"max":1,"chance":12.98396,"crystal":{"itemClassId":1864,"crystalType":"NoGrade","count":0},"npcType":1},{"npcId":20043,"min":1,"max":1,"chance":12.98396,"crystal":{"itemClassId":1868,"crystalType":"NoGrade","count":0},"npcType":1},{"npcId":20043,"min":1,"max":1,"chance":6.49195,"crystal":{"itemClassId":1865,"crystalType":"NoGrade","count":0},"npcType":1},{"npcId":20043,"min":1,"max":1,"chance":4.32797,"crystal":{"itemClassId":1866,"crystalType":"NoGrade","count":0},"npcType":1},{"npcId":20043,"min":1,"max":1,"chance":2.59682,"crystal":{"itemClassId":1873,"crystalType":"NoGrade","count":0},"npcType":1},{"npcId":20043,"min":1,"max":1,"chance":1.29838,"crystal":{"itemClassId":2143,"crystalType":"NoGrade","count":0},"npcType":1},{"npcId":20043,"min":1,"max":1,"chance":0.2705,"crystal":{"itemClassId":2012,"crystalType":"NoGrade","count":0},"npcType":1},{"npcId":20043,"min":1,"max":1,"chance":0.2597,"crystal":{"itemClassId":5158,"crystalType":"NoGrade","count":0},"npcType":1},{"npcId":20043,"min":1,"max":1,"chance":0.02473,"crystal":{"itemClassId":2,"crystalType":"NoGrade","count":0},"npcType":1},{"npcId":20043,"min":1,"max":1,"chance":0.02473,"crystal":{"itemClassId":120,"crystalType":"NoGrade","count":0},"npcType":1},{"npcId":20043,"min":1,"max":1,"chance":0.02473,"crystal":{"itemClassId":121,"crystalType":"NoGrade","count":0},"npcType":1}],"spoil":[{"npcId":20043,"min":1,"max":2,"chance":100,"crystal":{"itemClassId":1864,"crystalType":"NoGrade","count":0},"npcType":1},{"npcId":20043,"min":1,"max":1,"chance":28.3587,"crystal":{"itemClassId":1924,"crystalType":"NoGrade","count":0},"npcType":1},{"npcId":20043,"min":1,"max":1,"chance":17.5824,"crystal":{"itemClassId":1817,"crystalType":"NoGrade","count":0},"npcType":1}],"isLocationExist":true}