{"npcData":{"npcClassId":20420,"level":21,"npcType":1,"acquireExpRate":2338.829829,"acquireSp":108,"skillList":[{"skillId":4416,"skillLevel":9},{"skillId":4408,"skillLevel":1},{"skillId":4409,"skillLevel":1},{"skillId":4410,"skillLevel":12},{"skillId":4411,"skillLevel":12},{"skillId":4412,"skillLevel":10},{"skillId":4413,"skillLevel":10},{"skillId":4414,"skillLevel":2},{"skillId":4415,"skillLevel":3},{"skillId":4278,"skillLevel":1},{"skillId":4333,"skillLevel":5}],"magicList":[],"corpseMakeList":[{"itemClassId":1868,"min":1,"max":2,"chance":100},{"itemClassId":1866,"min":1,"max":1,"chance":58.09259999999999},{"itemClassId":1804,"min":1,"max":1,"chance":3.4857}],"additionalMakeList":[],"additionalMakeMultiList":[{"itemClassId":57,"min":339,"max":606,"chance":70},{"itemClassId":1102,"min":1,"max":1,"chance":0.1813002456},{"itemClassId":1105,"min":1,"max":1,"chance":0.29089975440000004},{"itemClassId":1864,"min":1,"max":1,"chance":17.159644085100002},{"itemClassId":1865,"min":1,"max":1,"chance":8.5797958455},{"itemClassId":1866,"min":1,"max":1,"chance":5.719863897},{"itemClassId":1873,"min":1,"max":1,"chance":3.4319183382},{"itemClassId":1868,"min":1,"max":1,"chance":17.159644085100002},{"itemClassId":5163,"min":1,"max":1,"chance":0.34323374910000004}],"exItemDropList":[],"orgHp":575,"orgMp":250,"baseDefend":89,"baseMagicAttack":30,"baseMagicDefend":72,"basePhysicalAttack":68,"physicalHitModify":0,"physicalAvoidModify":0,"baseAttackSpeed":253,"baseCritical":44,"social":true},"drop":[{"npcId":20420,"min":339,"max":606,"chance":70,"crystal":{"itemClassId":57,"crystalType":"NoGrade","count":0},"npcType":1},{"npcId":20420,"min":1,"max":1,"chance":17.15964,"crystal":{"itemClassId":1864,"crystalType":"NoGrade","count":0},"npcType":1},{"npcId":20420,"min":1,"max":1,"chance":17.15964,"crystal":{"itemClassId":1868,"crystalType":"NoGrade","count":0},"npcType":1},{"npcId":20420,"min":1,"max":1,"chance":8.5798,"crystal":{"itemClassId":1865,"crystalType":"NoGrade","count":0},"npcType":1},{"npcId":20420,"min":1,"max":1,"chance":5.71986,"crystal":{"itemClassId":1866,"crystalType":"NoGrade","count":0},"npcType":1},{"npcId":20420,"min":1,"max":1,"chance":3.43192,"crystal":{"itemClassId":1873,"crystalType":"NoGrade","count":0},"npcType":1},{"npcId":20420,"min":1,"max":1,"chance":0.34323,"crystal":{"itemClassId":5163,"crystalType":"NoGrade","count":0},"npcType":1},{"npcId":20420,"min":1,"max":1,"chance":0.2909,"crystal":{"itemClassId":1105,"crystalType":"NoGrade","count":0},"npcType":1},{"npcId":20420,"min":1,"max":1,"chance":0.1813,"crystal":{"itemClassId":1102,"crystalType":"NoGrade","count":0},"npcType":1}],"spoil":[{"npcId":20420,"min":1,"max":2,"chance":100,"crystal":{"itemClassId":1868,"crystalType":"NoGrade","count":0},"npcType":1},{"npcId":20420,"min":1,"max":1,"chance":58.0926,"crystal":{"itemClassId":1866,"crystalType":"NoGrade","count":0},"npcType":1},{"npcId":20420,"min":1,"max":1,"chance":3.4857,"crystal":{"itemClassId":1804,"crystalType":"NoGrade","count":0},"npcType":1}],"isLocationExist":true}