{"npcData":{"npcClassId":22020,"level":33,"npcType":1,"acquireExpRate":5102.243784,"acquireSp":291,"skillList":[{"skillId":4416,"skillLevel":3},{"skillId":4408,"skillLevel":1},{"skillId":4409,"skillLevel":1},{"skillId":4410,"skillLevel":12},{"skillId":4411,"skillLevel":11},{"skillId":4412,"skillLevel":12},{"skillId":4413,"skillLevel":11},{"skillId":4414,"skillLevel":2},{"skillId":4415,"skillLevel":3},{"skillId":4417,"skillLevel":4}],"magicList":[],"corpseMakeList":[{"itemClassId":1901,"min":1,"max":1,"chance":23.4855},{"itemClassId":2154,"min":1,"max":1,"chance":18.2052},{"itemClassId":1938,"min":1,"max":1,"chance":11.4309}],"additionalMakeList":[],"additionalMakeMultiList":[{"itemClassId":57,"min":717,"max":1437,"chance":70},{"itemClassId":58,"min":1,"max":1,"chance":0.018312167700000003},{"itemClassId":59,"min":1,"max":1,"chance":0.026473896000000004},{"itemClassId":349,"min":1,"max":1,"chance":0.018312167700000003},{"itemClassId":350,"min":1,"max":1,"chance":0.018312167700000003},{"itemClassId":351,"min":1,"max":1,"chance":0.0165419598},{"itemClassId":378,"min":1,"max":1,"chance":0.026473896000000004},{"itemClassId":379,"min":1,"max":1,"chance":0.0264737451},{"itemClassId":1872,"min":1,"max":1,"chance":24.108475104000004},{"itemClassId":1867,"min":1,"max":1,"chance":24.108475104000004},{"itemClassId":1881,"min":1,"max":1,"chance":2.4108475104},{"itemClassId":1875,"min":1,"max":1,"chance":1.2054237552},{"itemClassId":8302,"min":1,"max":1,"chance":0.1291785264}],"exItemDropList":[{"itemClassId":8600,"min":1,"max":1,"chance":23.1},{"itemClassId":8601,"min":1,"max":1,"chance":15.96},{"itemClassId":8611,"min":1,"max":1,"chance":10.34},{"itemClassId":8604,"min":1,"max":1,"chance":7.26},{"itemClassId":8606,"min":1,"max":1,"chance":5},{"itemClassId":8608,"min":1,"max":1,"chance":5},{"itemClassId":8610,"min":1,"max":1,"chance":5},{"itemClassId":8607,"min":1,"max":1,"chance":5},{"itemClassId":8609,"min":1,"max":1,"chance":5},{"itemClassId":8602,"min":1,"max":1,"chance":2.94},{"itemClassId":8603,"min":1,"max":1,"chance":2.53},{"itemClassId":8605,"min":1,"max":1,"chance":1.21},{"itemClassId":8614,"min":1,"max":1,"chance":0.34},{"itemClassId":8612,"min":1,"max":1,"chance":0.33},{"itemClassId":8613,"min":1,"max":1,"chance":0.33}],"orgHp":1109,"orgMp":455,"baseDefend":173,"baseMagicAttack":75,"baseMagicDefend":139,"basePhysicalAttack":181,"physicalHitModify":0,"physicalAvoidModify":0,"baseAttackSpeed":253,"baseCritical":44,"social":false},"drop":[{"npcId":22020,"min":717,"max":1437,"chance":70,"crystal":{"itemClassId":57,"crystalType":"NoGrade","count":0},"npcType":1},{"npcId":22020,"min":1,"max":1,"chance":24.10848,"crystal":{"itemClassId":1872,"crystalType":"NoGrade","count":0},"npcType":1},{"npcId":22020,"min":1,"max":1,"chance":24.10848,"crystal":{"itemClassId":1867,"crystalType":"NoGrade","count":0},"npcType":1},{"npcId":22020,"min":1,"max":1,"chance":2.41085,"crystal":{"itemClassId":1881,"crystalType":"NoGrade","count":0},"npcType":1},{"npcId":22020,"min":1,"max":1,"chance":1.20542,"crystal":{"itemClassId":1875,"crystalType":"NoGrade","count":0},"npcType":1},{"npcId":22020,"min":1,"max":1,"chance":0.12918,"crystal":{"itemClassId":8302,"crystalType":"NoGrade","count":0},"npcType":1},{"npcId":22020,"min":1,"max":1,"chance":0.02647,"crystal":{"itemClassId":59,"crystalType":"D","count":230},"npcType":1},{"npcId":22020,"min":1,"max":1,"chance":0.02647,"crystal":{"itemClassId":378,"crystalType":"D","count":230},"npcType":1},{"npcId":22020,"min":1,"max":1,"chance":0.02647,"crystal":{"itemClassId":379,"crystalType":"D","count":230},"npcType":1},{"npcId":22020,"min":1,"max":1,"chance":0.01831,"crystal":{"itemClassId":58,"crystalType":"D","count":332},"npcType":1},{"npcId":22020,"min":1,"max":1,"chance":0.01831,"crystal":{"itemClassId":349,"crystalType":"D","count":332},"npcType":1},{"npcId":22020,"min":1,"max":1,"chance":0.01831,"crystal":{"itemClassId":350,"crystalType":"D","count":332},"npcType":1},{"npcId":22020,"min":1,"max":1,"chance":0.01654,"crystal":{"itemClassId":351,"crystalType":"D","count":369},"npcType":1}],"spoil":[{"npcId":22020,"min":1,"max":1,"chance":23.4855,"crystal":{"itemClassId":1901,"crystalType":"NoGrade","count":0},"npcType":1},{"npcId":22020,"min":1,"max":1,"chance":18.2052,"crystal":{"itemClassId":2154,"crystalType":"NoGrade","count":0},"npcType":1},{"npcId":22020,"min":1,"max":1,"chance":11.4309,"crystal":{"itemClassId":1938,"crystalType":"NoGrade","count":0},"npcType":1}],"isLocationExist":true}