{"npcData":{"npcClassId":12272,"level":66,"npcType":1,"acquireExpRate":435.6,"acquireSp":1,"skillList":[{"skillId":4290,"skillLevel":1},{"skillId":4045,"skillLevel":1}],"magicList":[],"corpseMakeList":[],"additionalMakeList":[],"additionalMakeMultiList":[],"exItemDropList":[],"orgHp":35465,"orgMp":5415,"baseDefend":427,"baseMagicAttack":649,"baseMagicDefend":347,"basePhysicalAttack":3368,"physicalHitModify":0,"physicalAvoidModify":0,"baseAttackSpeed":216,"baseCritical":44,"social":true},"drop":[],"spoil":[],"isLocationExist":false}