{"npcData":{"npcClassId":1714,"level":50,"npcType":1,"acquireExpRate":8931.835000000001,"acquireSp":673,"skillList":[{"skillId":4298,"skillLevel":1},{"skillId":4304,"skillLevel":1},{"skillId":4278,"skillLevel":1},{"skillId":4333,"skillLevel":3},{"skillId":4285,"skillLevel":2},{"skillId":4275,"skillLevel":1}],"magicList":[],"corpseMakeList":[{"itemClassId":1977,"min":1,"max":1,"chance":4.3228},{"itemClassId":2231,"min":1,"max":1,"chance":1.2596},{"itemClassId":1978,"min":1,"max":1,"chance":18.732}],"additionalMakeList":[],"additionalMakeMultiList":[{"itemClassId":57,"min":1179,"max":2397,"chance":70},{"itemClassId":64,"min":1,"max":1,"chance":0.024662354},{"itemClassId":2956,"min":1,"max":1,"chance":1.777087646},{"itemClassId":608,"min":1,"max":1,"chance":0.024662354},{"itemClassId":1981,"min":1,"max":1,"chance":1.777087646},{"itemClassId":1895,"min":1,"max":1,"chance":5.754500180800001},{"itemClassId":4040,"min":1,"max":1,"chance":0.402815658},{"itemClassId":4042,"min":1,"max":1,"chance":0.3356756816},{"itemClassId":4043,"min":1,"max":1,"chance":0.67135943},{"itemClassId":2233,"min":1,"max":1,"chance":0.1882307112},{"itemClassId":2970,"min":1,"max":1,"chance":0.7142183384}],"exItemDropList":[],"orgHp":6735,"orgMp":830,"baseDefend":236,"baseMagicAttack":263,"baseMagicDefend":225,"basePhysicalAttack":445,"physicalHitModify":10,"physicalAvoidModify":0,"baseAttackSpeed":289,"baseCritical":88,"social":true},"drop":[{"npcId":1714,"min":1179,"max":2397,"chance":70,"crystal":{"itemClassId":57,"crystalType":"NoGrade","count":0},"npcType":1},{"npcId":1714,"min":1,"max":1,"chance":5.7545,"crystal":{"itemClassId":1895,"crystalType":"NoGrade","count":0},"npcType":1},{"npcId":1714,"min":1,"max":1,"chance":1.77709,"crystal":{"itemClassId":2956,"crystalType":"NoGrade","count":0},"npcType":1},{"npcId":1714,"min":1,"max":1,"chance":1.77709,"crystal":{"itemClassId":1981,"crystalType":"NoGrade","count":0},"npcType":1},{"npcId":1714,"min":1,"max":1,"chance":0.71422,"crystal":{"itemClassId":2970,"crystalType":"NoGrade","count":0},"npcType":1},{"npcId":1714,"min":1,"max":1,"chance":0.67136,"crystal":{"itemClassId":4043,"crystalType":"NoGrade","count":0},"npcType":1},{"npcId":1714,"min":1,"max":1,"chance":0.40282,"crystal":{"itemClassId":4040,"crystalType":"NoGrade","count":0},"npcType":1},{"npcId":1714,"min":1,"max":1,"chance":0.33568,"crystal":{"itemClassId":4042,"crystalType":"NoGrade","count":0},"npcType":1},{"npcId":1714,"min":1,"max":1,"chance":0.18823,"crystal":{"itemClassId":2233,"crystalType":"NoGrade","count":0},"npcType":1},{"npcId":1714,"min":1,"max":1,"chance":0.02466,"crystal":{"itemClassId":64,"crystalType":"C","count":98},"npcType":1},{"npcId":1714,"min":1,"max":1,"chance":0.02466,"crystal":{"itemClassId":608,"crystalType":"C","count":98},"npcType":1}],"spoil":[{"npcId":1714,"min":1,"max":1,"chance":18.732,"crystal":{"itemClassId":1978,"crystalType":"NoGrade","count":0},"npcType":1},{"npcId":1714,"min":1,"max":1,"chance":4.3228,"crystal":{"itemClassId":1977,"crystalType":"NoGrade","count":0},"npcType":1},{"npcId":1714,"min":1,"max":1,"chance":1.2596,"crystal":{"itemClassId":2231,"crystalType":"NoGrade","count":0},"npcType":1}],"isLocationExist":true}