{"npcData":{"npcClassId":526,"level":15,"npcType":1,"acquireExpRate":755.771625,"acquireSp":31,"skillList":[{"skillId":4291,"skillLevel":1},{"skillId":4071,"skillLevel":4},{"skillId":4273,"skillLevel":2},{"skillId":4274,"skillLevel":1},{"skillId":4116,"skillLevel":8},{"skillId":4284,"skillLevel":3}],"magicList":[],"corpseMakeList":[{"itemClassId":1833,"min":1,"max":1,"chance":69.4345},{"itemClassId":1921,"min":1,"max":1,"chance":16.7987},{"itemClassId":5220,"min":1,"max":1,"chance":1.0415}],"additionalMakeList":[],"additionalMakeMultiList":[{"itemClassId":57,"min":131,"max":199,"chance":70},{"itemClassId":114,"min":1,"max":1,"chance":0.1752966534},{"itemClassId":115,"min":1,"max":1,"chance":0.1752966534},{"itemClassId":907,"min":1,"max":1,"chance":0.1314730022},{"itemClassId":1896,"min":1,"max":1,"chance":1.3035876866},{"itemClassId":876,"min":1,"max":1,"chance":0.2629460044},{"itemClassId":1866,"min":1,"max":1,"chance":3.4183209411999997},{"itemClassId":1871,"min":1,"max":1,"chance":5.1274814118},{"itemClassId":1803,"min":1,"max":1,"chance":4.3087976470000005}],"exItemDropList":[],"orgHp":390,"orgMp":165,"baseDefend":83,"baseMagicAttack":14,"baseMagicDefend":122,"basePhysicalAttack":32,"physicalHitModify":0,"physicalAvoidModify":0,"baseAttackSpeed":253,"baseCritical":44,"social":true},"drop":[{"npcId":526,"min":131,"max":199,"chance":70,"crystal":{"itemClassId":57,"crystalType":"NoGrade","count":0},"npcType":1},{"npcId":526,"min":1,"max":1,"chance":5.12748,"crystal":{"itemClassId":1871,"crystalType":"NoGrade","count":0},"npcType":1},{"npcId":526,"min":1,"max":1,"chance":4.3088,"crystal":{"itemClassId":1803,"crystalType":"NoGrade","count":0},"npcType":1},{"npcId":526,"min":1,"max":1,"chance":3.41832,"crystal":{"itemClassId":1866,"crystalType":"NoGrade","count":0},"npcType":1},{"npcId":526,"min":1,"max":1,"chance":1.30359,"crystal":{"itemClassId":1896,"crystalType":"NoGrade","count":0},"npcType":1},{"npcId":526,"min":1,"max":1,"chance":0.26295,"crystal":{"itemClassId":876,"crystalType":"NoGrade","count":0},"npcType":1},{"npcId":526,"min":1,"max":1,"chance":0.1753,"crystal":{"itemClassId":114,"crystalType":"NoGrade","count":0},"npcType":1},{"npcId":526,"min":1,"max":1,"chance":0.1753,"crystal":{"itemClassId":115,"crystalType":"NoGrade","count":0},"npcType":1},{"npcId":526,"min":1,"max":1,"chance":0.13147,"crystal":{"itemClassId":907,"crystalType":"NoGrade","count":0},"npcType":1}],"spoil":[{"npcId":526,"min":1,"max":1,"chance":69.4345,"crystal":{"itemClassId":1833,"crystalType":"NoGrade","count":0},"npcType":1},{"npcId":526,"min":1,"max":1,"chance":16.7987,"crystal":{"itemClassId":1921,"crystalType":"NoGrade","count":0},"npcType":1},{"npcId":526,"min":1,"max":1,"chance":1.0415,"crystal":{"itemClassId":5220,"crystalType":"NoGrade","count":0},"npcType":1}],"isLocationExist":true}