{"npcData":{"npcClassId":533,"level":2,"npcType":1,"acquireExpRate":70.56,"acquireSp":2,"skillList":[{"skillId":4293,"skillLevel":1}],"magicList":[],"corpseMakeList":[{"itemClassId":1872,"min":1,"max":1,"chance":2.3887},{"itemClassId":1872,"min":1,"max":1,"chance":2.3887},{"itemClassId":5549,"min":1,"max":1,"chance":0.17919999999999997}],"additionalMakeList":[],"additionalMakeMultiList":[{"itemClassId":57,"min":8,"max":13,"chance":70},{"itemClassId":13,"min":1,"max":1,"chance":0.48230000000000006},{"itemClassId":1868,"min":1,"max":1,"chance":0.9261136016},{"itemClassId":1873,"min":1,"max":1,"chance":0.185221716},{"itemClassId":1787,"min":1,"max":1,"chance":0.3704459428},{"itemClassId":1060,"min":1,"max":1,"chance":1.0290187396000001}],"exItemDropList":[],"orgHp":75,"orgMp":52,"baseDefend":41,"baseMagicAttack":3,"baseMagicDefend":33,"basePhysicalAttack":9,"physicalHitModify":0,"physicalAvoidModify":0,"baseAttackSpeed":253,"baseCritical":44,"social":false},"drop":[{"npcId":533,"min":8,"max":13,"chance":70,"crystal":{"itemClassId":57,"crystalType":"NoGrade","count":0},"npcType":1},{"npcId":533,"min":1,"max":1,"chance":1.02902,"crystal":{"itemClassId":1060,"crystalType":"NoGrade","count":0},"npcType":1},{"npcId":533,"min":1,"max":1,"chance":0.92611,"crystal":{"itemClassId":1868,"crystalType":"NoGrade","count":0},"npcType":1},{"npcId":533,"min":1,"max":1,"chance":0.4823,"crystal":{"itemClassId":13,"crystalType":"NoGrade","count":0},"npcType":1},{"npcId":533,"min":1,"max":1,"chance":0.37045,"crystal":{"itemClassId":1787,"crystalType":"NoGrade","count":0},"npcType":1},{"npcId":533,"min":1,"max":1,"chance":0.18522,"crystal":{"itemClassId":1873,"crystalType":"NoGrade","count":0},"npcType":1}],"spoil":[{"npcId":533,"min":1,"max":1,"chance":2.3887,"crystal":{"itemClassId":1872,"crystalType":"NoGrade","count":0},"npcType":1},{"npcId":533,"min":1,"max":1,"chance":2.3887,"crystal":{"itemClassId":1872,"crystalType":"NoGrade","count":0},"npcType":1},{"npcId":533,"min":1,"max":1,"chance":0.1792,"crystal":{"itemClassId":5549,"crystalType":"NoGrade","count":0},"npcType":1}],"isLocationExist":true}