{"npcData":{"npcClassId":960,"level":64,"npcType":1,"acquireExpRate":3994.3168,"acquireSp":366,"skillList":[{"skillId":4298,"skillLevel":1},{"skillId":4311,"skillLevel":1},{"skillId":4275,"skillLevel":3},{"skillId":4278,"skillLevel":1}],"magicList":[],"corpseMakeList":[{"itemClassId":4052,"min":1,"max":1,"chance":4.7533},{"itemClassId":5230,"min":1,"max":1,"chance":0.179},{"itemClassId":4053,"min":1,"max":1,"chance":5.7546}],"additionalMakeList":[],"additionalMakeMultiList":[{"itemClassId":57,"min":544,"max":1100,"chance":70},{"itemClassId":97,"min":1,"max":1,"chance":0.0003026716},{"itemClassId":4115,"min":1,"max":1,"chance":0.0864973284},{"itemClassId":1873,"min":1,"max":1,"chance":1.9828592546},{"itemClassId":1868,"min":1,"max":1,"chance":9.9142533084},{"itemClassId":1876,"min":1,"max":1,"chance":0.9914296273},{"itemClassId":1895,"min":1,"max":1,"chance":1.416328039},{"itemClassId":4042,"min":1,"max":1,"chance":0.0826209258},{"itemClassId":5230,"min":1,"max":1,"chance":0.0066165484},{"itemClassId":5276,"min":1,"max":1,"chance":0.0066165484},{"itemClassId":1343,"min":10,"max":30,"chance":7.081575748099999}],"exItemDropList":[],"orgHp":1692,"orgMp":1285,"baseDefend":345,"baseMagicAttack":588,"baseMagicDefend":331,"basePhysicalAttack":1031,"physicalHitModify":10,"physicalAvoidModify":0,"baseAttackSpeed":253,"baseCritical":11,"social":true},"drop":[{"npcId":960,"min":544,"max":1100,"chance":70,"crystal":{"itemClassId":57,"crystalType":"NoGrade","count":0},"npcType":1},{"npcId":960,"min":1,"max":1,"chance":9.91425,"crystal":{"itemClassId":1868,"crystalType":"NoGrade","count":0},"npcType":1},{"npcId":960,"min":10,"max":30,"chance":7.08158,"crystal":{"itemClassId":1343,"crystalType":"B","count":0},"npcType":1},{"npcId":960,"min":1,"max":1,"chance":1.98286,"crystal":{"itemClassId":1873,"crystalType":"NoGrade","count":0},"npcType":1},{"npcId":960,"min":1,"max":1,"chance":1.41633,"crystal":{"itemClassId":1895,"crystalType":"NoGrade","count":0},"npcType":1},{"npcId":960,"min":1,"max":1,"chance":0.99143,"crystal":{"itemClassId":1876,"crystalType":"NoGrade","count":0},"npcType":1},{"npcId":960,"min":1,"max":1,"chance":0.0865,"crystal":{"itemClassId":4115,"crystalType":"NoGrade","count":0},"npcType":1},{"npcId":960,"min":1,"max":1,"chance":0.08262,"crystal":{"itemClassId":4042,"crystalType":"NoGrade","count":0},"npcType":1},{"npcId":960,"min":1,"max":1,"chance":0.00662,"crystal":{"itemClassId":5230,"crystalType":"NoGrade","count":0},"npcType":1},{"npcId":960,"min":1,"max":1,"chance":0.00662,"crystal":{"itemClassId":5276,"crystalType":"NoGrade","count":0},"npcType":1},{"npcId":960,"min":1,"max":1,"chance":0.0003,"crystal":{"itemClassId":97,"crystalType":"B","count":1746},"npcType":1}],"spoil":[{"npcId":960,"min":1,"max":1,"chance":5.7546,"crystal":{"itemClassId":4053,"crystalType":"NoGrade","count":0},"npcType":1},{"npcId":960,"min":1,"max":1,"chance":4.7533,"crystal":{"itemClassId":4052,"crystalType":"NoGrade","count":0},"npcType":1},{"npcId":960,"min":1,"max":1,"chance":0.179,"crystal":{"itemClassId":5230,"crystalType":"NoGrade","count":0},"npcType":1}],"isLocationExist":false}